json_pyformatter/__init__.py
json_pyformatter/formatter.py
json_pyformatter-0.1.0.dist-info/LICENSE
json_pyformatter-0.1.0.dist-info/WHEEL
json_pyformatter-0.1.0.dist-info/METADATA
json_pyformatter-0.1.0.dist-info/RECORD
