Metadata-Version: 2.1
Name: json-pyformatter
Version: 0.1.0
Summary: Python logging module outputs logs as JSON.
Home-page: https://github.com/homoluctus/json-pyformatter
License: MIT
Keywords: python,json,logging,formatter
Author: homoluctus
Author-email: w.slife18sy@gmail.com
Requires-Python: >=3.7,<4.0
Classifier: Development Status :: 5 - Production/Stable
Classifier: License :: OSI Approved :: MIT License
Classifier: Programming Language :: Python
Classifier: Programming Language :: Python :: 3
Classifier: Programming Language :: Python :: 3.7
Classifier: Programming Language :: Python :: 3.8
Project-URL: Repository, https://github.com/homoluctus/json-pyformatter
